flook/__init__.py
flook/cli.py
flook/command/__init__.py
flook/command/configs.py
flook/command/hosts.py
flook/command/recipes.py
flook/exception/__init__.py
flook/model/__init__.py
flook/model/host.py
flook/model/recipe.py
flook/model/task.py
flook/module/__init__.py
flook/module/config.py
flook/module/database.py
flook/module/file_system.py
flook/module/logger.py
flook/module/output.py
flook/module/playbook.py
flook-0.4.1.dist-info/LICENSE.txt
flook-0.4.1.dist-info/METADATA
flook-0.4.1.dist-info/WHEEL
flook-0.4.1.dist-info/entry_points.txt
flook-0.4.1.dist-info/top_level.txt
flook-0.4.1.dist-info/RECORD
