Metadata-Version: 2.1
Name: flook
Version: 0.4.1
Summary: A Lightweight and Flexible Ansible Command Line Tool.
Home-page: https://github.com/norwik/flook/
Author: Clivern
Author-email: hello@clivern.com
License: MIT
Project-URL: Documentation, https://github.com/norwik/flook/
Project-URL: Source, https://github.com/norwik/flook/
Project-URL: Changelog, https://github.com/norwik/flook/blob/main/CHANGELOG.rst
Project-URL: Tracker, https://github.com/norwik/flook/issues
Project-URL: Download, https://pypi.org/project/flook/#files
Platform: any
Classifier: Development Status :: 5 - Production/Stable
Classifier: Programming Language :: Python
Classifier: License :: OSI Approved :: MIT License
License-File: LICENSE.txt
Requires-Dist: click (<=8.1.3)
Requires-Dist: ansible-runner (<=2.3.3)
Requires-Dist: prettytable (<=3.8.0)
Requires-Dist: PyYAML (<=6.0)
Requires-Dist: importlib-metadata (<=6.7.0) ; python_version < "3.8"
